tws_simple_package/__init__.py
tws_simple_package/tws_simple_package.py
tws_simple_package-0.1.1.dist-info/entry_points.txt
tws_simple_package-0.1.1.dist-info/WHEEL
tws_simple_package-0.1.1.dist-info/METADATA
tws_simple_package-0.1.1.dist-info/RECORD
