Metadata-Version: 2.1
Name: tws-simple-package
Version: 0.1.1
Summary: Simple Poetry Package
Author: Taylor Santiago
Author-email: tsanti928@gmail.com
Requires-Python: >=3.9,<4.0
Classifier: Programming Language :: Python :: 3
Classifier: Programming Language :: Python :: 3.10
Classifier: Programming Language :: Python :: 3.9
Requires-Dist: jsonschema (>=4.4.0,<5.0.0)
